pgpipe/__init__.py
pgpipe/admixture.py
pgpipe/argparse_sets.py
pgpipe/bcftools.py
pgpipe/beagle.py
pgpipe/bed_invert.py
pgpipe/bed_utilities.py
pgpipe/bedtools_wrapper.py
pgpipe/eigenstrat_fstats.py
pgpipe/eigenstrat_wrapper.py
pgpipe/extend_loci.py
pgpipe/fasta.py
pgpipe/fasta_utilities.py
pgpipe/filter_single_vcf.py
pgpipe/genome_region.py
pgpipe/get_nonmissing_chunks.py
pgpipe/graph_plotter.py
pgpipe/ima3_wrapper.py
pgpipe/ima_priors.py
pgpipe/ima_to_treemix.py
pgpipe/informative_loci_filter.py
pgpipe/logging_module.py
pgpipe/min_pop_filter.py
pgpipe/misc.py
pgpipe/model.py
pgpipe/model_creator.py
pgpipe/model_sampler.py
pgpipe/parse_functions.py
pgpipe/picard.py
pgpipe/plink.py
pgpipe/plink_linkage_disequilibrium.py
pgpipe/shapeit.py
pgpipe/site_stats.py
pgpipe/stat_sampler.py
pgpipe/subtract_bed.py
pgpipe/test_cython.pyx
pgpipe/vcf_bed_to_seq.py
pgpipe/vcf_calc.py
pgpipe/vcf_filter.py
pgpipe/vcf_filter_vcftools.py
pgpipe/vcf_format_conversions.py
pgpipe/vcf_four_gamete.py
pgpipe/vcf_liftover.py
pgpipe/vcf_phase.py
pgpipe/vcf_reader_func.py
pgpipe/vcf_ref_to_seq.py
pgpipe/vcf_split.py
pgpipe/vcf_split_pysam.py
pgpipe/vcf_to_dadi.py
pgpipe/vcf_to_fastsimcoal.py
pgpipe/vcf_to_gphocs.py
pgpipe/vcf_to_ima.py
pgpipe/vcf_to_sfs.py
pgpipe/vcf_to_treemix.py
pgpipe/vcf_utilities.py
pgpipe/vcftools.py
py_popgen-0.1.10.data/scripts/admixture.py
py_popgen-0.1.10.data/scripts/bed_utilities.py
py_popgen-0.1.10.data/scripts/eigenstrat_fstats.py
py_popgen-0.1.10.data/scripts/ima3_wrapper.py
py_popgen-0.1.10.data/scripts/informative_loci_filter.py
py_popgen-0.1.10.data/scripts/model_creator.py
py_popgen-0.1.10.data/scripts/plink_linkage_disequilibrium.py
py_popgen-0.1.10.data/scripts/stat_sampler.py
py_popgen-0.1.10.data/scripts/vcf_bed_to_seq.py
py_popgen-0.1.10.data/scripts/vcf_calc.py
py_popgen-0.1.10.data/scripts/vcf_filter.py
py_popgen-0.1.10.data/scripts/vcf_format_conversions.py
py_popgen-0.1.10.data/scripts/vcf_four_gamete.py
py_popgen-0.1.10.data/scripts/vcf_phase.py
py_popgen-0.1.10.dist-info/METADATA
py_popgen-0.1.10.dist-info/WHEEL
py_popgen-0.1.10.dist-info/top_level.txt
py_popgen-0.1.10.dist-info/RECORD
