Metadata-Version: 2.1
Name: py-popgen
Version: 0.1.10
Summary: Software platform for facilitating population genomic analyses
Home-page: https://ppp.csusm.edu/
Author: Andrew Webb, Jared Knoblauch, Nitesh Sabankar, Apeksha Sukesh Kallur, Jody Hey and Arun Sethuraman
Author-email: asethuraman@csusm.edu
Maintainer: Jared Knoblauch, Andrew Webb
Maintainer-email: tug41380@temple.edu
License: MIT
Project-URL: Documentation, https://ppp.readthedocs.io
Project-URL: Code, https://github.com/jaredgk/PPP
Project-URL: Issue tracker, https://github.com/jaredgk/PPP/issues
Platform: UNKNOWN
Requires-Python: >=3.6.*, !=3.8.*
Requires-Dist: Cython
Requires-Dist: pysam
Requires-Dist: pandas
Requires-Dist: pybedtools
Requires-Dist: scikit-learn
Requires-Dist: matplotlib
